rproxy/__init__.py
rproxy/_version.py
rproxy-18.6.0.dist-info/DESCRIPTION.rst
rproxy-18.6.0.dist-info/METADATA
rproxy-18.6.0.dist-info/RECORD
rproxy-18.6.0.dist-info/WHEEL
rproxy-18.6.0.dist-info/metadata.json
rproxy-18.6.0.dist-info/top_level.txt
twisted/plugins/rproxy.py
