Metadata-Version: 2.0
Name: rproxy
Version: 18.6.0
Summary: A super simple reverse proxy.
Home-page: UNKNOWN
Author: Amber Brown
Author-email: hawkowl@atleastfornow.net
License: UNKNOWN
Platform: UNKNOWN
Requires-Dist: twisted[tls] (>=18.4.0)
Requires-Dist: pyopenssl
Requires-Dist: txsni
Requires-Dist: txacme
Requires-Dist: incremental
